bettersocket/__init__.py
bettersocket/bettersocket.py
bettersocket-0.1.1.dist-info/AUTHORS.rst
bettersocket-0.1.1.dist-info/LICENSE
bettersocket-0.1.1.dist-info/METADATA
bettersocket-0.1.1.dist-info/WHEEL
bettersocket-0.1.1.dist-info/top_level.txt
bettersocket-0.1.1.dist-info/RECORD
