Metadata-Version: 2.1
Name: bettersocket
Version: 0.1.1
Summary: Better socket handling for Python3
Home-page: https://github.com/marcsello/bettersocket
Author: Marcsello Hooves
Author-email: punkosdmarcell@rocketmail.com
License: MIT license
Keywords: bettersocket
Platform: UNKNOWN
Classifier: Development Status :: 2 - Pre-Alpha
Classifier: Intended Audience :: Developers
Classifier: License :: OSI Approved :: MIT License
Classifier: Natural Language :: English
Classifier: Programming Language :: Python :: 3
Classifier: Programming Language :: Python :: 3.6
Classifier: Programming Language :: Python :: 3.7
Classifier: Programming Language :: Python :: 3.8
Requires-Python: >=3.6
